setup.py
Inventicode.egg-info/PKG-INFO
Inventicode.egg-info/SOURCES.txt
Inventicode.egg-info/SOURCES.txt.py
Inventicode.egg-info/dependency_links.txt
Inventicode.egg-info/dependency_links.txt.py
Inventicode.egg-info/entry_points.txt
Inventicode.egg-info/entry_points.txt.py
Inventicode.egg-info/not-zip-safe
Inventicode.egg-info/requires.txt
Inventicode.egg-info/requires.txt.py
Inventicode.egg-info/top_level.txt
Inventicode.egg-info/top_level.txt.py
inventicode/__init__.py
inventicode/admin.py
inventicode/defaults.py
inventicode/forms.py
inventicode/iniconf.py
inventicode/models.py
inventicode/urls.py
inventicode/views.py
inventicode/migrations/0001_initial.py
inventicode/migrations/0002_printpaper_background.py
inventicode/migrations/0003_printpaper_template.py
inventicode/migrations/0004_auto_20170222_2352.py
inventicode/migrations/0005_auto_20170223_1939.py
inventicode/migrations/0006_auto_20170223_1946.py
inventicode/migrations/0007_auto_20170223_1948.py
inventicode/migrations/0008_auto_20170223_1949.py
inventicode/migrations/0009_printpaper_css.py
inventicode/migrations/0010_auto_20170224_1934.py
inventicode/migrations/0011_auto_20170225_0929.py
inventicode/migrations/0012_remove_element_reference.py
inventicode/migrations/0013_auto_20170225_1526.py
inventicode/migrations/__init__.py
inventicode/templatetags/__init__.py
inventicode/templatetags/inventicode.py