Metadata-Version: 1.1
Name: Inventicode
Version: 1.0.1
Summary: Create labels with QR and barcodes.
Home-page: https://github.com/d9pouces/inventicode
Author: mgallet
Author-email: github@19pouces.net
License: CeCILL-B
Platform: UNKNOWN
Classifier: Development Status :: 3 - Alpha
Classifier: Operating System :: MacOS :: MacOS X
Classifier: Operating System :: Microsoft :: Windows
Classifier: Operating System :: POSIX :: BSD
Classifier: Operating System :: POSIX :: Linux
Classifier: Operating System :: Unix
Classifier: License :: OSI Approved :: CEA CNRS Inria Logiciel Libre License, version 2.1 (CeCILL-2.1)
Classifier: Programming Language :: Python :: 3.4
Classifier: Programming Language :: Python :: 3.5
Classifier: Programming Language :: Python :: 3.6
